LICENSE
README.md
setup.py
ppRank/__init__.py
ppRank/bilex.py
ppRank/par10.py
ppRank.egg-info/PKG-INFO
ppRank.egg-info/SOURCES.txt
ppRank.egg-info/dependency_links.txt
ppRank.egg-info/requires.txt
ppRank.egg-info/top_level.txt